elis/__init__.py
elis-0.0.1rc1.dist-info/licenses/LICENSE
elis-0.0.1rc1.dist-info/METADATA
elis-0.0.1rc1.dist-info/WHEEL
elis-0.0.1rc1.dist-info/top_level.txt
elis-0.0.1rc1.dist-info/RECORD
