Metadata-Version: 2.4
Name: elis
Version: 0.0.1rc1
Summary: Me.
Author-email: "Elis K." <opensource@elis.cc>
License: MIT License
Project-URL: Homepage, https://github.com/el1s7
Keywords: elis
Requires-Python: >=3.9
License-File: LICENSE
Dynamic: license-file
